tracedy/Sampler.py
tracedy/__init__.py
tracedy/_task_manager/ingestion_consumer.py
tracedy/_task_manager/media_manager.py
tracedy/_task_manager/media_upload_consumer.py
tracedy/_task_manager/media_upload_queue.py
tracedy/_task_manager/task_manager.py
tracedy/api/README.md
tracedy/api/__init__.py
tracedy/api/client.py
tracedy/api/core/__init__.py
tracedy/api/core/api_error.py
tracedy/api/core/client_wrapper.py
tracedy/api/core/datetime_utils.py
tracedy/api/core/file.py
tracedy/api/core/http_client.py
tracedy/api/core/jsonable_encoder.py
tracedy/api/core/pydantic_utilities.py
tracedy/api/core/query_encoder.py
tracedy/api/core/remove_none_from_dict.py
tracedy/api/core/request_options.py
tracedy/api/reference.md
tracedy/api/resources/__init__.py
tracedy/api/resources/annotation_queues/__init__.py
tracedy/api/resources/annotation_queues/client.py
tracedy/api/resources/annotation_queues/types/__init__.py
tracedy/api/resources/annotation_queues/types/annotation_queue.py
tracedy/api/resources/annotation_queues/types/annotation_queue_item.py
tracedy/api/resources/annotation_queues/types/annotation_queue_object_type.py
tracedy/api/resources/annotation_queues/types/annotation_queue_status.py
tracedy/api/resources/annotation_queues/types/create_annotation_queue_item_request.py
tracedy/api/resources/annotation_queues/types/delete_annotation_queue_item_response.py
tracedy/api/resources/annotation_queues/types/paginated_annotation_queue_items.py
tracedy/api/resources/annotation_queues/types/paginated_annotation_queues.py
tracedy/api/resources/annotation_queues/types/update_annotation_queue_item_request.py
tracedy/api/resources/comments/__init__.py
tracedy/api/resources/comments/client.py
tracedy/api/resources/comments/types/__init__.py
tracedy/api/resources/comments/types/create_comment_request.py
tracedy/api/resources/comments/types/create_comment_response.py
tracedy/api/resources/comments/types/get_comments_response.py
tracedy/api/resources/commons/__init__.py
tracedy-1.1.0.dist-info/METADATA
tracedy-1.1.0.dist-info/WHEEL
tracedy-1.1.0.dist-info/entry_points.txt
tracedy-1.1.0.dist-info/RECORD
